janus/__init__.py
janus/channels.py
janus/compartments.py
janus/discretization.py
janus/graph_util.py
janus/graphics_util.py
janus/morphology.py
janus/perisomal.py
janus/util.py
janus_sim-0.0.1.dist-info/LICENSE
janus_sim-0.0.1.dist-info/METADATA
janus_sim-0.0.1.dist-info/WHEEL
janus_sim-0.0.1.dist-info/top_level.txt
janus_sim-0.0.1.dist-info/RECORD
