Metadata-Version: 2.1
Name: janus-sim
Version: 0.0.1
Summary: A JAX Neural Simulator
Author-email: Dieterich Lawson <dieterich.lawson@gmail.com>
License: MIT License
Project-URL: repository, https://github.com/dieterichlawson/janus
Classifier: Programming Language :: Python :: 3.9
Classifier: Programming Language :: Python :: 3.10
Classifier: Programming Language :: Python :: 3.11
Classifier: License :: OSI Approved :: MIT License
Classifier: Operating System :: OS Independent
Classifier: Development Status :: 2 - Pre-Alpha
Requires-Python: >=3.9
License-File: LICENSE
Requires-Dist: jax (>=0.4.6)
Requires-Dist: jaxlib (>=0.4.6)
Requires-Dist: jaxtyping
Requires-Dist: numpy
Requires-Dist: equinox
Provides-Extra: test
Requires-Dist: pytest ; extra == 'test'
Requires-Dist: neuron ; extra == 'test'
